smart_automation/__init__.py
smart_automation/accessibility.py
smart_automation/base_page.py
smart_automation/config.py
smart_automation/data.py
smart_automation/driver.py
smart_automation/events.py
smart_automation/exceptions.py
smart_automation/logger.py
smart_automation/mobile_driver.py
smart_automation/performance.py
smart_automation/plugins.py
smart_automation/reporting.py
smart_automation/utils.py
smart_automation_utils-0.2.0.dist-info/licenses/LICENSE
tests/__init__.py
tests/test_basic.py
tests/test_data.py
tests/test_performance.py
tests/test_pom.py
smart_automation_utils-0.2.0.dist-info/METADATA
smart_automation_utils-0.2.0.dist-info/WHEEL
smart_automation_utils-0.2.0.dist-info/top_level.txt
smart_automation_utils-0.2.0.dist-info/RECORD
