Metadata-Version: 2.4
Name: smart-automation-utils
Version: 0.2.0
Summary: A python package for automation developers working with Selenium and Appium
Home-page: https://www.dhirajdas.dev
Author: dhiraj
Author-email: gowebdk@gmail.com
Classifier: Programming Language :: Python :: 3
Classifier: License :: OSI Approved :: MIT License
Classifier: Operating System :: OS Independent
Requires-Python: >=3.6
License-File: LICENSE
Requires-Dist: selenium>=4.0.0
Requires-Dist: Appium-Python-Client
Requires-Dist: psutil
Requires-Dist: webdriver-manager
Requires-Dist: pytest
Requires-Dist: pytest-glow-report
Requires-Dist: waitless
Dynamic: author
Dynamic: author-email
Dynamic: classifier
Dynamic: description
Dynamic: description-content-type
Dynamic: home-page
Dynamic: license-file
Dynamic: requires-dist
Dynamic: requires-python
Dynamic: summary
